puentestayro/__init__.py
puentestayro/matematicas.py
puentestayro-0.1.0.dist-info/METADATA
puentestayro-0.1.0.dist-info/WHEEL
puentestayro-0.1.0.dist-info/RECORD
