Metadata-Version: 2.1
Name: puentestayro
Version: 0.1.0
Summary: Paquete de ejemplo
Author: tayrocorrea
Author-email: tcorrealoaiza@gmail.com
Requires-Python: >=3.10.0,<3.12
Classifier: Programming Language :: Python :: 3
Classifier: Programming Language :: Python :: 3.10
Classifier: Programming Language :: Python :: 3.11
